ChatAgent/__init__.py
ChatAgent/serve.py
ChatAgent/agent_wrappers/__init__.py
ChatAgent/agent_wrappers/base_agent_wrapper.py
ChatAgent/agent_wrappers/multimodal2text.py
ChatAgent/agent_wrappers/prompt2chat.py
ChatAgent/agent_wrappers/retry_in_choices.py
ChatAgent/agent_wrappers/save_request.py
ChatAgent/agents/__init__.py
ChatAgent/agents/azure_chat_agent.py
ChatAgent/agents/base_agent.py
ChatAgent/agents/base_api_agent.py
ChatAgent/agents/base_chat_api_agent.py
ChatAgent/agents/base_completion_api_agent.py
ChatAgent/agents/dashscope_chat_agent.py
ChatAgent/agents/dashscope_multimodal_chat_agent.py
ChatAgent/agents/empty_openai_agent.py
ChatAgent/agents/openai_chat2completion_agent.py
ChatAgent/agents/openai_chat_agent.py
ChatAgent/agents/random_openai_agent.py
ChatAgent/agents/repeat_openai_chat_agent.py
ChatAgent/agents/simple_multimodal_query.py
ChatAgent/agents/zhipu_chat_agent.py
ChatAgent/chat_api_protocol/__init__.py
ChatAgent/protocol/__init__.py
ChatAgent/protocol/api_protocol.py
ChatAgent/protocol/openai_api_protocol.py
ChatAgent/rag/__init__.py
ChatAgent/rag/utils.py
ChatAgent/test_api/__init__.py
ChatAgent/test_api/chat_completion.py
ChatAgent/utils/__init__.py
ChatAgent/utils/logger.py
ChatAgent/utils/multimodality_tools.py
ChatAgent/utils/qwen.py
ChatAgent/utils/request_utils.py
ChatAgent/utils/response_utils.py
ChatAgent/vec_agents/__init__.py
ChatAgent/vec_agents/async_vagent.py
ChatAgent/vec_agents/base_vagent.py
ChatAgent/vec_agents/sync_vagent.py
ChatAgent/vec_agents/wrappers/__init__.py
ChatAgent/vec_agents/wrappers/base_vec_wrapper.py
ChatAgent_python-0.0.1.dist-info/LICENSE
ChatAgent_python-0.0.1.dist-info/METADATA
ChatAgent_python-0.0.1.dist-info/WHEEL
ChatAgent_python-0.0.1.dist-info/top_level.txt
ChatAgent_python-0.0.1.dist-info/RECORD
